{
  "label_counts": {
    "부정": 75170,
    "긍정": 74825
  },
  "length_histogram": {
    "bin_edges": [
      1.0,
      8.2,
      15.5,
      22.8,
      30.0,
      37.2,
      44.5,
      51.8,
      59.0,
      66.2,
      73.5,
      80.8,
      88.0,
      95.2,
      102.5,
      109.8,
      117.0,
      124.2,
      131.5,
      138.8,
      146.0
    ],
    "counts": [
      11413,
      25353,
      25224,
      20874,
      19657,
      13894,
      8042,
      3973,
      3576,
      2522,
      2116,
      1874,
      1793,
      1343,
      1208,
      1023,
      1185,
      1176,
      2121,
      1628
    ]
  },
  "top_words_by_label": {
    "부정": [
      [
        "영화",
        4878
      ],
      [
        "없다",
        2243
      ],
      [
        "아니다",
        1032
      ],
      [
        "로",
        963
      ],
      [
        "너무",
        947
      ],
      [
        "진짜",
        907
      ],
      [
        "만들다",
        898
      ],
      [
        "아깝다",
        859
      ],
      [
        "점",
        834
      ],
      [
        "같다",
        833
      ],
      [
        "않다",
        766
      ],
      [
        "안",
        752
      ],
      [
        "나오다",
        751
      ],
      [
        "평점",
        709
      ],
      [
        "못",
        709
      ],
      [
        "쓰레기",
        698
      ],
      [
        "적",
        689
      ],
      [
        "재미없다",
        689
      ],
      [
        "스토리",
        679
      ],
      [
        "정말",
        639
      ]
    ],
    "긍정": [
      [
        "영화",
        5301
      ],
      [
        "좋다",
        1767
      ],
      [
        "재밌다",
        1576
      ],
      [
        "정말",
        1304
      ],
      [
        "너무",
        1299
      ],
      [
        "최고",
        1103
      ],
      [
        "적",
        1053
      ],
      [
        "같다",
        913
      ],
      [
        "없다",
        869
      ],
      [
        "진짜",
        834
      ],
      [
        "감동",
        803
      ],
      [
        "않다",
        756
      ],
      [
        "재미있다",
        730
      ],
      [
        "연기",
        724
      ],
      [
        "점",
        672
      ],
      [
        "생각",
        666
      ],
      [
        "로",
        656
      ],
      [
        "인",
        636
      ],
      [
        "내",
        620
      ],
      [
        "때",
        610
      ]
    ]
  },
  "word_tokenizer": "okt"
}